hellopypi_oh.py
hellopypi_oh-0.1.0.dist-info/METADATA
hellopypi_oh-0.1.0.dist-info/WHEEL
hellopypi_oh-0.1.0.dist-info/entry_points.txt
hellopypi_oh-0.1.0.dist-info/top_level.txt
hellopypi_oh-0.1.0.dist-info/RECORD
