Metadata-Version: 2.1
Name: hellopypi_oh
Version: 0.1.0
Summary: print Hello Pypi in terminal.
Home-page: https://github.com/Taot-chen/hellopypi_oh
Author: oehuosi
Author-email: oehuosi@foxmail.com
License: MIT
Classifier: License :: OSI Approved :: MIT License
Classifier: Programming Language :: Python
Classifier: Programming Language :: Python :: 3
Classifier: Programming Language :: Python :: 3.6
Classifier: Programming Language :: Python :: Implementation :: CPython
Classifier: Programming Language :: Python :: Implementation :: PyPy
Requires-Python: >=3.6.0
